beewi_smartclim/__init__.py
beewi_smartclim-0.0.10.dist-info/LICENSE
beewi_smartclim-0.0.10.dist-info/METADATA
beewi_smartclim-0.0.10.dist-info/WHEEL
beewi_smartclim-0.0.10.dist-info/top_level.txt
beewi_smartclim-0.0.10.dist-info/RECORD
