Metadata-Version: 2.1
Name: beewi-smartclim
Version: 0.0.10
Summary: Library to read data from BeeWi SmartClim sensor using Bluetooth LE
Home-page: https://github.com/alemuro/beewi_smartclim
Author: alemuro
Author-email: hello@aleix.cloud
License: MIT
Keywords: temperature and humidity sensor bluetooth low-energy ble beewi smartclim
Platform: UNKNOWN
Classifier: Programming Language :: Python :: 3
Classifier: License :: OSI Approved :: MIT License
Classifier: Operating System :: OS Independent
Requires-Python: >=3.5
Requires-Dist: btlewrap (>=0.0.8)
Requires-Dist: bluepy
